bos/__init__.py
bos/bosminer/__init__.py
bos/bosminer/client.py
bos/bosplusapi/__init__.py
bos/bosplusapi/client.py
bosminer-1.3.0.dist-info/METADATA
bosminer-1.3.0.dist-info/WHEEL
bosminer-1.3.0.dist-info/RECORD
