Metadata-Version: 2.1
Name: bosminer
Version: 1.3.0
Summary: 
Author: teosibileau
Author-email: teo.sibileau@gmail.com
Requires-Python: >=3.8,<4.0
Classifier: Programming Language :: Python :: 3
Classifier: Programming Language :: Python :: 3.8
Classifier: Programming Language :: Python :: 3.9
Classifier: Programming Language :: Python :: 3.10
Classifier: Programming Language :: Python :: 3.11
Requires-Dist: grpc-requests (>=0.1.10,<0.2.0)
